Metadata-Version: 1.0
Name: hello-mattmoony
Version: 0.1.0
Summary: Hello World - Python app
Home-page: UNKNOWN
Author: Matthias M.
Author-email: m4ttm00ny@gmail.com
License: UNKNOWN
Platform: UNKNOWN
